setup.py
evzookeeper/__init__.py
evzookeeper/membership.py
evzookeeper/queue.py
evzookeeper/utils.py
evzookeeper.egg-info/PKG-INFO
evzookeeper.egg-info/SOURCES.txt
evzookeeper.egg-info/dependency_links.txt
evzookeeper.egg-info/top_level.txt