Metadata-Version: 1.0
Name: evzookeeper
Version: 0.4.0
Summary: zookeeper binding for eventlet
Home-page: https://github.com/maoy/python-evzookeeper
Author: Yun Mao
Author-email: yunmao@gmail.com
License: Apache License (2.0)
Keywords: zookeeper eventlet
Platform: UNKNOWN
Classifier: Programming Language :: Python
